sammy_poetry/__init__.py
sammy_poetry-0.1.0.dist-info/WHEEL
sammy_poetry-0.1.0.dist-info/METADATA
sammy_poetry-0.1.0.dist-info/RECORD
